{
    "AX": {
        "error": 0.0,
        "fit": "default",
        "references": [],
        "value": 1.0
    },
    "CDD": {
        "error": 0.0021992461022158146,
        "fit": "Average",
        "reference_data": {
            "es": [
                0.0012207988915178985,
                0.001054210427499998,
                0.0009776034682047537,
                0.001047521247943182,
                0.00092142084390509,
                0.0010068235284250895
            ],
            "vs": [
                0.9657349862558353,
                0.9834493154071157,
                0.9714266035557692,
                0.9621689895528991,
                0.9617581255257192,
                0.9657879806971974
            ],
            "xs": [
                1693320434.0,
                1693328414.0,
                1693382488.0,
                1693390503.0,
                1693401050.0,
                1693411600.0
            ]
        },
        "reference_detector": "H1",
        "references": [
            {
                "exclude": "ok",
                "record_id": "a-01-A-8083",
                "uuid": "b9815941-bb45-484f-82c5-de306629e81a"
            },
            {
                "exclude": "omit",
                "record_id": "a-01-A-8084",
                "uuid": "487a7763-be26-4734-ab97-12332759a5ee"
            },
            {
                "exclude": "omit",
                "record_id": "a-01-A-8085",
                "uuid": "cc8a94e2-b12f-4b15-b12e-4c22b06b8fad"
            },
            {
                "exclude": "ok",
                "record_id": "a-01-A-8086",
                "uuid": "7baa3e58-c57e-4674-aeb8-9df68dcced1b"
            },
            {
                "exclude": "ok",
                "record_id": "a-01-A-8087",
                "uuid": "072d3c29-7fe4-449b-a12a-19f9548b24b1"
            },
            {
                "exclude": "ok",
                "record_id": "a-01-A-8088",
                "uuid": "0313e02d-fa48-4266-bdb1-f2811d955f6f"
            }
        ],
        "reviewed": true,
        "standard_ratio": 295.5,
        "value": 0.9638625205079128
    },
    "H1": {
        "error": 0.0,
        "fit": "default",
        "references": [],
        "value": 1.0
    },
    "L1": {
        "error": 0.0,
        "fit": "default",
        "references": [],
        "value": 1.0
    },
    "L2": {
        "error": 0.0,
        "fit": "default",
        "references": [],
        "value": 1.0
    }
}